Metadata-Version: 2.4
Name: mcp-server-peliqan
Version: 0.1.0
Summary: MCP Server for Peliqan.io
Requires-Python: >=3.12
Requires-Dist: httpx>=0.28.1
Requires-Dist: mcp[cli]>=1.5.0
